README.rst
setup.py
bin/mlgw_fit_NN
bin/mlgw_generate_angle_dataset
bin/mlgw_generate_dataset
bin/mlgw_tune_NN
bin/mlgw_write_training_dag
mlgw/EM_MoE.py
mlgw/GW_generator.py
mlgw/GW_helper.py
mlgw/ML_routines.py
mlgw/NN_model.py
mlgw/__init__.py
mlgw/fit_model.py
mlgw/precession_helper.py
mlgw.egg-info/PKG-INFO
mlgw.egg-info/SOURCES.txt
mlgw.egg-info/dependency_links.txt
mlgw.egg-info/requires.txt
mlgw.egg-info/top_level.txt
mlgw/TD_models/model_0/README
mlgw/TD_models/model_0/21/Model_fit_info_01.txt
mlgw/TD_models/model_0/21/Model_fit_info_0123.txt
mlgw/TD_models/model_0/21/Model_fit_info_01_residual.txt
mlgw/TD_models/model_0/21/Model_fit_info_2345.txt
mlgw/TD_models/model_0/21/amp_PCA_model.dat
mlgw/TD_models/model_0/21/amp_weights_0123.keras
mlgw/TD_models/model_0/21/ph_PCA_model.dat
mlgw/TD_models/model_0/21/ph_weights_01.keras
mlgw/TD_models/model_0/21/ph_weights_01_residual.keras
mlgw/TD_models/model_0/21/ph_weights_2345.keras
mlgw/TD_models/model_0/21/residual_coefficients_01
mlgw/TD_models/model_0/21/times.dat
mlgw/TD_models/model_0/22/Model_fit_info_01.txt
mlgw/TD_models/model_0/22/Model_fit_info_0123.txt
mlgw/TD_models/model_0/22/Model_fit_info_01_residual.txt
mlgw/TD_models/model_0/22/Model_fit_info_2345.txt
mlgw/TD_models/model_0/22/amp_PCA_model.dat
mlgw/TD_models/model_0/22/amp_weights_0123.keras
mlgw/TD_models/model_0/22/ph_PCA_model.dat
mlgw/TD_models/model_0/22/ph_weights_01.keras
mlgw/TD_models/model_0/22/ph_weights_01_residual.keras
mlgw/TD_models/model_0/22/ph_weights_2345.keras
mlgw/TD_models/model_0/22/residual_coefficients_01
mlgw/TD_models/model_0/22/times.dat
mlgw/TD_models/model_0/33/Model_fit_info_01.txt
mlgw/TD_models/model_0/33/Model_fit_info_0123.txt
mlgw/TD_models/model_0/33/Model_fit_info_01_residual.txt
mlgw/TD_models/model_0/33/Model_fit_info_2345.txt
mlgw/TD_models/model_0/33/amp_PCA_model.dat
mlgw/TD_models/model_0/33/amp_weights_0123.keras
mlgw/TD_models/model_0/33/ph_PCA_model.dat
mlgw/TD_models/model_0/33/ph_weights_01.keras
mlgw/TD_models/model_0/33/ph_weights_01_residual.keras
mlgw/TD_models/model_0/33/ph_weights_2345.keras
