Metadata-Version: 2.1
Name: mlgw
Version: 3.0.1
Summary: Machine learning modelling of the gravitational waves generated by black-hole binaries
Home-page: https://github.com/stefanoschmidt1995/MLGW/
Author: Stefano Schmidt
Author-email: stefanoschmidt1995@gmail.com
License: CC by 4.0
Platform: UNKNOWN
